Blauwal3_Explain-0.6.10-py3.10-nspkg.pth
orangecontrib/explain/__init__.py
orangecontrib/explain/explainer.py
orangecontrib/explain/i18n_config.py
orangecontrib/explain/inspection.py
orangecontrib/explain/locale/explain.de.yml
orangecontrib/explain/locale/explain.en.yml
orangecontrib/explain/locale/explain.zh.yml
orangecontrib/explain/tests/__init__.py
orangecontrib/explain/tests/test_explainer.py
orangecontrib/explain/tests/test_inspection.py
orangecontrib/explain/widgets/__init__.py
orangecontrib/explain/widgets/owexplainfeaturebase.py
orangecontrib/explain/widgets/owexplainmodel.py
orangecontrib/explain/widgets/owexplainprediction.py
orangecontrib/explain/widgets/owexplainpredictions.py
orangecontrib/explain/widgets/owice.py
orangecontrib/explain/widgets/owpermutationimportance.py
orangecontrib/explain/widgets/icons/ExplainModel.svg
orangecontrib/explain/widgets/icons/ExplainPred.svg
orangecontrib/explain/widgets/icons/ExplainPredictions.svg
orangecontrib/explain/widgets/icons/ICE.svg
orangecontrib/explain/widgets/icons/PermutationImportance.svg
orangecontrib/explain/widgets/tests/__init__.py
orangecontrib/explain/widgets/tests/test_owexplainmodel.py
orangecontrib/explain/widgets/tests/test_owexplainprediction.py
orangecontrib/explain/widgets/tests/test_owexplainpredictions.py
orangecontrib/explain/widgets/tests/test_owice.py
orangecontrib/explain/widgets/tests/test_owpermutationimportance.py
Blauwal3_Explain-0.6.10.dist-info/LICENSE.txt
Blauwal3_Explain-0.6.10.dist-info/METADATA
Blauwal3_Explain-0.6.10.dist-info/WHEEL
Blauwal3_Explain-0.6.10.dist-info/entry_points.txt
Blauwal3_Explain-0.6.10.dist-info/namespace_packages.txt
Blauwal3_Explain-0.6.10.dist-info/top_level.txt
Blauwal3_Explain-0.6.10.dist-info/RECORD
